###\u52A0\u8F7D\u548C\u5B58\u50A8\u6307\u4EE4
#\u5C40\u90E8\u53D8\u91CF\u52A0\u8F7D\u5230\u64CD\u4F5C\u6570\u6808
iload,21,0x15
iload_<0>,26,0x1a
iload_<1>,27,0x1b
iload_<2>,28,0x1c
iload_<3>,29,0x1d
lload,22,ox16
lload_<0>,30,0x1e
lload_<1>,31,0x1f
lload_<2>,32,0x20
lload_<3>,33,0x21
fload,23,0x17
fload_<0>,34,0x22
fload_<1>,35,0x23
fload_<2>,36,0x24
fload_<3>,37,0x25
dload,24,0x18
#\u4ECE\u5C40\u90E8\u53D8\u91CF\u8868\u52A0\u8F7D\u4E00\u4E2A double \u7C7B\u578B\u503C\u5230\u64CD\u4F5C\u6570\u6808\u4E2D
dload_<0>,38,0x26
dload_<1>,39,0x27
dload_<2>,40,0x28
dload_<3>,41,0x29
aload,25,0x19
aload_<0>,42,0x2a
aload_<1>,43,0x2b
aload_<2>,44,0x2c
aload_<3>,45,0x2d
#\u4ECE\u64CD\u4F5C\u6570\u6808\u5B58\u50A8\u5230\u5C40\u90E8\u53D8\u91CF\u8868
istore,54,0x36
istore_<0>,59,0x3b
istore_<1>,60,0x3c
istore_<2>,61,0x3d
istore_<3>,62,0x3e
lstore,55,0x37
lstore_<0>,63,0x3f
lstore_<1>,64,0x40
lstore_<2>,65,0x41
lstore_<3>,66,0x42
fstore,56,0x38
fstore_<0>,67,0x43
fstore_<1>,68,0x44
fstore_<2>,69,0x45
fstore_<3>,70,0x46
dstore,57,0x39
dstore_<0>,71,0x47
dstore_<1>,72,0x48
dstore_<2>,73,0x49
dstore_<3>,74,0x4a
astore,58,0x3a
astore_<0>,75,0x4b
astore_<1>,76,0x4c
astore_<2>,77,0x4d
astore_<3>,78,0x4e
#\u5E38\u91CF\u52A0\u8F7D\u5230\u64CD\u4F5C\u6570\u6808
bipush,16,0x10
sipush,17,0x11
ldc,18,0x12
ldc_w,19,0x13
ldc2_w,20,0x14
aconst_null,1,0x01
#iconst_<n>:\u5C06int\u7C7B\u578B\u63A8\u9001\u81F3\u6808\u9876
iconst_m1,2,0x02
iconst_<0>,3,0x03
iconst_<1>,4,0x04
iconst_<2>,5,0x05
iconst_<3>,6,0x06
iconst_<4>,7,0x07
iconst_<5>,8,0x08
#lconst_<n>:\u5C06long\u7C7B\u578B\u63A8\u9001\u81F3\u6808\u9876
lconst_<0>,9,0x09
lconst_<1>,10,0x0a
#\u5C06float\u578B\u63A8\u9001\u81F3\u6808\u9876
fconst_<0>,11,0x0b
fconst_<1>,12,0x0c
fconst_<2>,13,0x0d
#\u5C06double\u578B\u63A8\u9001\u81F3\u6808\u9876
dconst_<0>,14,0x0e
dconst_<1>,15,0x0f
#\u8FD0\u7B97\u6307\u4EE4
#\u52A0\u6CD5\u6307\u4EE4
iadd,96,0x60
ladd,97,0x61
fadd,98,0x62
dadd,99,0x63 !!!
#\u51CF\u6CD5\u6307\u4EE4
isub,100,0x64
lsub,101,0x65
fsub,102,0x66
dsub,103,0x67
#\u4E58\u6CD5\u6307\u4EE4
imul,104,0x68
lmul,105,0x69
fmul,106,0x6a
dmul,107,0x6b
#\u9664\u6CD5\u6307\u4EE4
idiv,108,0x6c
ldiv,109,0x6d
fdiv,110,0x6e
ddiv,111,0x6f
#\u6C42\u4F59\u6307\u4EE4
irem,112,0x70
lrem,113,0x71
frem,114,0x72
drem,115,0x73
#\u53D6\u53CD\u6307\u4EE4
ineg,116,0x74
lneg,117,0x75
fneg,118,0x76
dneg,119,0x77
#\u4F4D\u79FB\u6307\u4EE4
ishl,120,0x78
ishr,122,0x7a
iushr,124,0x7c
lshl,121,0x79
lshr,123,0x7b
lushr,125,0x7d
#\u6309\u4F4D\u6216\u6307\u4EE4
ior,128,0x80
lor,129,0x81
#\u6309\u4F4D\u4E0E\u6307\u4EE4
iand,126,0x7e
land,127,0x7f
#\u6309\u4F4D\u5F02\u6216\u6307\u4EE4
ixor,130,0x82
lxor,131,0x83
#\u5C40\u90E8\u53D8\u91CF\u81EA\u589E\u6307\u4EE4
iinc,132,0x84
#\u6BD4\u8F83\u6307\u4EE4
dcmpg,152,0x98
dcmpl,151,0x97
fcmpg,150,0x96
fcmpl,149,0x95
lcmp,148,0x94
###\u7C7B\u578B\u8F6C\u6362\u6307\u4EE4
#\u5BBD\u5316\u7C7B\u578B\u8F6C\u6362,int-long,float-double
i2l,133,0x85
i2f,134,0x86
i2d,135,0x87
l2f,137,0x89,
l2d,138,0x8a
f2d,141,0x8d
#\u7A84\u5316\u7C7B\u578B\u8F6C\u6362 int-float
i2b,145,0x91
i2c,146,0x92
i2s,147,0x93
l2i,136,0x88
f2i,139,0x8b
f2l,140,0x8c
d2i,142,0x8e
d2l,143,0x8f
d2f,144,0x90
###\u5BF9\u8C61\u521B\u5EFA\u4E0E\u8BBF\u95EE\u6307\u4EE4
#\u521B\u5EFA\u7C7B\u5B9E\u4F8B\u7684\u6307\u4EE4
new,187,0xbb
#\u521B\u5EFA\u6570\u7EC4\u7684\u6307\u4EE4
newarray,188,0xbc
anewarray,189,0xbd
multianewarray,197,0xc5
#\u8BBF\u95EEstatic\u7C7B\u578B\u7684\u5B57\u6BB5
getstatic,178,0xb2
putstatic,179,0xb3
#\u8BBF\u95EE\u975Estatic\u7C7B\u578B\u7684\u5B57\u6BB5
getfield,180,0xb4
putfield,181,0xb5
#\u628A\u4E00\u4E2A\u6570\u7EC4\u5143\u7D20\u52A0\u8F7D\u5230\u64CD\u4F5C\u6570\u6808
baload,51,0x33
caload,52,0x34
saload,53,0x35
iaload,46,0x2e
laload,47,0x2f
faload,48,0x30
daload,49,0x31
aaload,50,0x32
#\u5C06\u4E00\u4E2A\u64CD\u4F5C\u6570\u6808\u7684\u503C\u5B58\u50A8\u5230\u6570\u7EC4\u5143\u7D20\u4E2D\u7684\u6307\u4EE4
bastore,84,0x54
castore,85,0x55
sastore,86,0x56
iastore,79,0x4f
fastore,81,0x51
dastore,82,0x52
aastore,83,0x53
#\u53D6\u6570\u7EC4\u957F\u5EA6\u7684\u6307\u4EE4
arraylength,190,0xbe
#\u68C0\u67E5\u7C7B\u5B9E\u4F8B\u7C7B\u578B\u7684\u6307\u4EE4
instanceof,193,0xc1
checkcast,192,0xc0
###\u64CD\u4F5C\u6570\u6808\u7BA1\u7406\u6307\u4EE4
#\u5C06\u64CD\u4F5C\u6570\u6808\u9876\u7684\u5143\u7D20\u4E00\u4E2A\u6216\u4E24\u4E2A\u51FA\u6808
pop,87,0x57
pop2,88,0x58
#\u590D\u5236\u4E00\u4E2A\u6808\u9876\u5143\u7D20\u6216\u8005\u4E24\u4E2A\u6808\u9876\u5143\u7D20\u91CD\u65B0\u5165\u6808
dup,89,0x59
dup2,92,0x5c
dup_x1,90,0x5a
dup2_x1,93,0x5d
dup_x2,91,0x5b
dup2_x2,94,0x5e
#\u5C06\u6808\u6700\u9876\u7AEF\u7684\u4E24\u4E2A\u5143\u7D20\u4E92\u6362
swap,95,0x5f
###\u63A7\u5236\u8F6C\u79FB\u6307\u4EE4
#\u6761\u4EF6\u5206\u652F
ifeq,153,0x99
iflt,154,0x9a
ifle,155,0x9b
ifne,156,0x9c
ifgt,157,0x9d
ifge,158,0x9e
ifnull,198,0xc6
ifnonnull,199,0xc7
if_icmpeq,159,0x9f
if_icmpne,160,0xa0
if_icmplt,161,0xa1
if_icmpgt,162,0xa2
if_icmple,163,0xa3
if_icmpge,164,0xa4
if_acmpeq,165,0xa5
if_acmpne,166,0xa6
#\u590D\u5408\u6761\u4EF6\u5206\u652F
tableswitch,170,0xaa
lookupswitch,171,0xab
#\u65E0\u6761\u4EF6\u5206\u652F
goto,167,0xa7
goto_w,200,0xc8
jsr,168,0xa8
jsr_w,201,0xc9
ret,169,0xa9
###\u65B9\u6CD5\u8C03\u7528\u548C\u8FD4\u56DE\u6307\u4EE4
#\u8C03\u7528\u5BF9\u8C61\u7684\u5B9E\u4F8B\u65B9\u6CD5
invokevirtual,182,0xb6
#\u7528\u4E8E\u8C03\u7528\u63A5\u53E3\u65B9\u6CD5
invokeinterface,185,0xb9
#\u7528\u4E8E\u8C03\u7528\u4E00\u4E9B\u9700\u8981\u7279\u6B8A\u5904\u7406\u7684\u5B9E\u4F8B\u65B9\u6CD5\uFF0C\u5305\u62EC\u5B9E\u4F8B\u521D\u59CB\u5316\uFF08\uFF1Cinit\uFF1E\uFF09\u65B9\u6CD5\u3001\u79C1\u6709\u65B9\u6CD5\u548C\u7236\u7C7B\u65B9\u6CD5
invokespecial,183,0xb7
#\u8C03\u7528\u9759\u6001\u65B9\u6CD5
invokestatic,184,0xb8
#\u8FD0\u884C\u65F6\u52A8\u6001\u89E3\u6790\u5F15\u7528\u65B9\u6CD5\uFF0C\u52A8\u6001\u8C03\u7528
invokedynamic,186,0xba
###\u5F02\u5E38\u5904\u7406\u6307\u4EE4
athrow,191,0xbf
###\u540C\u6B65\u6307\u4EE4
monitorenter,194,0xc2
monitorexit,195,0xc3
#exclude
areturn,176,0xb0
dreturn,175,0xaf
freturn,174,0xae
ireturn,172,0xac
return,177,0xb1
#
lastore,80,0x50
lreturn,173,0xad
#
nop,0,0x00
#
wide,196,0xc4











